myhumblepy/__init__.py
myhumblepy/utils_pandas.py
myhumblepy-0.0.1.dist-info/LICENSE
myhumblepy-0.0.1.dist-info/METADATA
myhumblepy-0.0.1.dist-info/WHEEL
myhumblepy-0.0.1.dist-info/RECORD
